automonkey/__init__.py
automonkey/app_funcs.py
automonkey/automonkey.py
automonkey/constants.py
automonkey/exceptions.py
automonkey/img_funcs.py
automonkey/mouse_tracker.py
automonkey/utils.py
AutoMonkey-0.1.5.dist-info/AUTHORS.rst
AutoMonkey-0.1.5.dist-info/LICENSE
AutoMonkey-0.1.5.dist-info/METADATA
AutoMonkey-0.1.5.dist-info/WHEEL
AutoMonkey-0.1.5.dist-info/entry_points.txt
AutoMonkey-0.1.5.dist-info/top_level.txt
AutoMonkey-0.1.5.dist-info/RECORD
