Metadata-Version: 2.1
Name: AutoMonkey
Version: 0.1.5
Summary: Python Automation using Mouse and Keyboard, for the masses
Home-page: https://github.com/MihailCosmin/automonkey
Author: Mihail-Cosmin Munteanu
Author-email: Mihail-Cosmin Munteanu <munteanumihailcosmin@gmail.com>
License: GNU General Public License v3
Project-URL: Homepage, https://github.com/MihailCosmin/AutoMonkey
Project-URL: Bug Tracker, https://github.com/MihailCosmin/AutoMonkey/issues
Keywords: automonkey
Classifier: Programming Language :: Python :: 3
Classifier: License :: OSI Approved :: MIT License
Classifier: Operating System :: OS Independent
Requires-Python: >=3.6
License-File: LICENSE
License-File: AUTHORS.rst
Requires-Dist: pyautogui (>=0.9.53)
Requires-Dist: pytesseract (>=0.3.9)
Requires-Dist: numpy (>=1.21.5)
Requires-Dist: keyboard (>=0.13.5)
Requires-Dist: clipboard (>=0.0.4)
Requires-Dist: opencv-python (==4.5.5.62)
Requires-Dist: pillow (>=9.0.1)
Requires-Dist: screeninfo (>=0.8)
Requires-Dist: pyperclip (==1.8.2)
Requires-Dist: PyScreeze (>=0.1.27)
Requires-Dist: pywin32 (>=303) ; platform_system == "Windows"
Requires-Dist: pywin32-ctypes (>=0.2.0) ; platform_system == "Windows"
